terminal_print/__init__.py
terminal_print/color.py
terminal_print/decorator.py
terminal_print/printer.py
terminal_plus-1.0.0.dev0.dist-info/LICENSE
terminal_plus-1.0.0.dev0.dist-info/METADATA
terminal_plus-1.0.0.dev0.dist-info/WHEEL
terminal_plus-1.0.0.dev0.dist-info/top_level.txt
terminal_plus-1.0.0.dev0.dist-info/RECORD
