Metadata-Version: 2.1
Name: terminal-plus
Version: 1.0.0.dev0
Summary: print plus
Author: ali
Author-email: lynali@gmail.com
Requires-Python: >=3.7.0
License-File: LICENSE
